[
	{"codigo":"US", "pais":"Estados Unidos"},
	{"codigo":"AD", "pais":"Andorra"},
	{"codigo":"AI", "pais":"Anguila"},
	{"codigo":"AR", "pais":"Argentina"},
	{"codigo":"AU", "pais":"Australia"},
	{"codigo":"AT", "pais":"Austria"},
	{"codigo":"AZ", "pais":"Azerbaiyán"},
	{"codigo":"BS", "pais":"Bahamas"},
	{"codigo":"BH", "pais":"Baréin"},
	{"codigo":"BB", "pais":"Barbados"},
	{"codigo":"BE", "pais":"Bélgica"},
	{"codigo":"BM", "pais":"Bermuda"},
	{"codigo":"BR", "pais":"Brasil"},
	{"codigo":"BG", "pais":"Bulgaria"},
	{"codigo":"CA", "pais":"Canadá"},
	{"codigo":"CL", "pais":"Chile"},
	{"codigo":"CN", "pais":"China"},
	{"codigo":"CO", "pais":"Colombia"},
	{"codigo":"CR", "pais":"Costa Rica"},
	{"codigo":"HR", "pais":"Croacia"},
	{"codigo":"CY", "pais":"Chipre"},
	{"codigo":"CZ", "pais":"República Checa"},
	{"codigo":"DK", "pais":"Dinamarca"},
	{"codigo":"DO", "pais":"República Dominicana"},
	{"codigo":"EC", "pais":"Ecuador"},
	{"codigo":"EE", "pais":"Estonia"},
	{"codigo":"FO", "pais":"Islas Feroe"},
	{"codigo":"FI", "pais":"Finlandia"},
	{"codigo":"FR", "pais":"Francia"},
	{"codigo":"GE", "pais":"Georgia"},
	{"codigo":"DE", "pais":"Alemania"},
	{"codigo":"GH", "pais":"Ghana"},
	{"codigo":"GI", "pais":"Gibraltar"},
	{"codigo":"GB", "pais":"Reino Unido"},
	{"codigo":"GR", "pais":"Grecia"},
	{"codigo":"HK", "pais":"Hong Kong"},
	{"codigo":"HU", "pais":"Hungría"},
	{"codigo":"IS", "pais":"Islandia"},
	{"codigo":"IN", "pais":"India"},
	{"codigo":"IE", "pais":"Irlanda"},
	{"codigo":"IL", "pais":"Israel"},
	{"codigo":"IT", "pais":"Italia"},
	{"codigo":"JM", "pais":"Jamaica"},
	{"codigo":"JP", "pais":"Japón"},
	{"codigo":"KR", "pais":"Corea del Sur"},
	{"codigo":"LV", "pais":"Letonia"},
	{"codigo":"LB", "pais":"Líbano"},
	{"codigo":"LT", "pais":"Lituania"},
	{"codigo":"LU", "pais":"Luxemburgo"},
	{"codigo":"MY", "pais":"Malasia"},
	{"codigo":"MT", "pais":"Malta"},
	{"codigo":"MX", "pais":"México"},
	{"codigo":"MC", "pais":"Mónaco"},
	{"codigo":"ME", "pais":"Montenegro"},
	{"codigo":"MA", "pais":"Marruecos"},
	{"codigo":"NL", "pais":"Países Bajos"},
	{"codigo":"AN", "pais":"Antillas"},
	{"codigo":"NZ", "pais":"Nueva Zelanda"},
	{"codigo":"ND", "pais":"Irlanda del Norte"},
	{"codigo":"NO", "pais":"Noruega"},
	{"codigo":"PE", "pais":"Perú"},
	{"codigo":"PL", "pais":"Polonia"},
	{"codigo":"PT", "pais":"Portugal"},
	{"codigo":"RO", "pais":"Rumanía"},
	{"codigo":"RU", "pais":"Rusia"},
	{"codigo":"LC", "pais":"Santa Lucía"},
	{"codigo":"SA", "pais":"Arabia Saudí"},
	{"codigo":"RS", "pais":"Serbia"},
	{"codigo":"SG", "pais":"Singapur"},
	{"codigo":"SK", "pais":"Eslovaquia"},
	{"codigo":"SI", "pais":"Eslovenia"},
	{"codigo":"ZA", "pais":"Sudáfrica"},
	{"codigo":"ES", "pais":"España"},
	{"codigo":"SE", "pais":"Suecia"},
	{"codigo":"CH", "pais":"Suiza"},
	{"codigo":"TW", "pais":"Taiwán"},
	{"codigo":"TH", "pais":"Tailandia"},
	{"codigo":"TT", "pais":"Trinidad y Tobago"},
	{"codigo":"TR", "pais":"Turquía"},
	{"codigo":"UA", "pais":"Ucrania"},
	{"codigo":"AE", "pais":"Emiratos Árabes Unidos"},
	{"codigo":"UY", "pais":"Uruguay"},
	{"codigo":"VE", "pais":"Venezuela"}
]